pipuserstats/LICENSE
pipuserstats/README.md
pipuserstats/__init__.py
pipuserstats/requirements.txt
pipuserstats/thirdparty.json
pipuserstats-0.10.dist-info/LICENSE.rst
pipuserstats-0.10.dist-info/METADATA
pipuserstats-0.10.dist-info/WHEEL
pipuserstats-0.10.dist-info/top_level.txt
pipuserstats-0.10.dist-info/RECORD
