Metadata-Version: 2.1
Name: pipuserstats
Version: 0.10
Summary: PyPi download statistics for several packages or for all packages from a user
Home-page: https://github.com/hansalemaos/pipuserstats
Author: Johannes Fischer
Author-email: aulasparticularesdealemaosp@gmail.com
License: MIT
Keywords: pypi,stats
Classifier: Development Status :: 4 - Beta
Classifier: Programming Language :: Python :: 3 :: Only
Classifier: Programming Language :: Python :: 3.10
Classifier: Topic :: Software Development :: Libraries :: Python Modules
Classifier: Topic :: Utilities
License-File: LICENSE.rst
Requires-Dist: beautifulsoup4
Requires-Dist: cprinter
Requires-Dist: list-all-files-recursively
Requires-Dist: pandas
Requires-Dist: platformdirs
Requires-Dist: pypistats
Requires-Dist: Requests
